{"description":"user should be able to add new category successfully|New category addition","passed":true,"pending":false,"os":"Windows NT","instanceId":2588,"browser":{"name":"chrome","version":"78.0.3904.97"},"message":"Passed","browserLogs":[{"level":"SEVERE","message":"https://api.ordercloud.io/v1/catalogs/pn/categories - Failed to load resource: the server responded with a status of 409 (Conflict)","timestamp":1573967545589,"type":""},{"level":"SEVERE","message":"https://archway-premiernutrition-seller-qa.azurewebsites.net/vendor.js 57254:18 \"ERROR\" HttpErrorResponse","timestamp":1573967545589,"type":""}],"screenShotFile":"009d0042-003c-0016-00c9-000f00dd00fe.png","timestamp":1573967535759,"duration":9824}
